{
  "format_version": "1.12.0",
  "minecraft:geometry": [
    {
      "description": {
        "identifier": "geometry.goblin",
        "texture_width": 64,
        "texture_height": 64,
        "visible_bounds_width": 4,
        "visible_bounds_height": 3,
        "visible_bounds_offset": [
          0,
          1.5,
          0
        ]
      },
      "bones": [
        {
          "name": "root",
          "pivot": [
            0,
            0,
            0
          ]
        },
        {
          "name": "waist",
          "parent": "root",
          "pivot": [
            0,
            12,
            0
          ]
        },
        {
          "name": "body",
          "parent": "waist",
          "pivot": [
            0,
            24,
            0
          ],
          "cubes": [
            {
              "origin": [
                -2,
                4,
                -1
              ],
              "size": [
                4,
                5,
                2
              ],
              "uv": [
                0,
                12
              ]
            }
          ]
        },
        {
          "name": "head",
          "parent": "body",
          "pivot": [
            0,
            10,
            0
          ],
          "cubes": [
            {
              "origin": [
                -4,
                9,
                -3
              ],
              "size": [
                8,
                6,
                6
              ],
              "uv": [
                0,
                0
              ]
            },
            {
              "origin": [
                4,
                10,
                1
              ],
              "size": [
                3,
                3,
                0
              ],
              "uv": [
                22,
                3
              ]
            },
            {
              "origin": [
                -7,
                10,
                1
              ],
              "size": [
                3,
                3,
                0
              ],
              "uv": [
                22,
                0
              ]
            },
            {
              "origin": [
                -2,
                15,
                -1
              ],
              "size": [
                4,
                3,
                4
              ],
              "uv": [
                48,
                0
              ]
            }
          ]
        },
        {
          "name": "leftArm",
          "parent": "body",
          "pivot": [
            2,
            8,
            0
          ],
          "cubes": [
            {
              "origin": [
                2,
                4,
                -1
              ],
              "size": [
                2,
                5,
                2
              ],
              "uv": [
                20,
                12
              ]
            }
          ]
        },
        {
          "name": "leftItem",
          "parent": "leftArm",
          "pivot": [
            3,
            5,
            -1
          ]
        },
        {
          "name": "rightArm",
          "parent": "body",
          "pivot": [
            -2,
            8,
            0
          ],
          "cubes": [
            {
              "origin": [
                -4,
                4,
                -1
              ],
              "size": [
                2,
                5,
                2
              ],
              "uv": [
                12,
                12
              ]
            }
          ]
        },
        {
          "name": "rightItem",
          "parent": "rightArm",
          "pivot": [
            -3,
            6,
            -1
          ],
          "locators": {
            "lead_hold": [
              -3,
              6,
              0
            ]
          }
        },
        {
          "name": "leftLeg",
          "parent": "root",
          "pivot": [
            0,
            4,
            0
          ],
          "cubes": [
            {
              "origin": [
                0,
                0,
                -1
              ],
              "size": [
                2,
                4,
                2
              ],
              "uv": [
                8,
                19
              ]
            }
          ]
        },
        {
          "name": "rightLeg",
          "parent": "root",
          "pivot": [
            0,
            4,
            0
          ],
          "cubes": [
            {
              "origin": [
                -2,
                0,
                -1
              ],
              "size": [
                2,
                4,
                2
              ],
              "uv": [
                0,
                19
              ]
            }
          ]
        }
      ]
    }
  ]
}